toms_structures/__init__.py
toms_structures/_masonry.py
toms_structures/_reinforced_masonry.py
toms_structures/_util.py
toms_structures/reinforced_masonry.py
toms_structures/unreinforced_masonry.py
toms_structures-0.0.39.dist-info/METADATA
toms_structures-0.0.39.dist-info/WHEEL
toms_structures-0.0.39.dist-info/licenses/LICENSE
toms_structures-0.0.39.dist-info/RECORD
