Metadata-Version: 2.4
Name: toms_structures
Version: 0.0.39
Summary: A collection of scripts for structural engineering design
Project-URL: Homepage, https://github.com/pypa/sampleproject
Project-URL: Issues, https://github.com/pypa/sampleproject/issues
Author-email: Thomas Duffett <thomasduffett4@gmail.com>
License-File: LICENSE
Classifier: Development Status :: 3 - Alpha
Classifier: Operating System :: OS Independent
Classifier: Programming Language :: Python :: 3.12
Requires-Python: >=3.12
Requires-Dist: concreteproperties>=0.7.0
Requires-Dist: ipynbname
Requires-Dist: nbsphinx
Requires-Dist: pydantic
Requires-Dist: pytest
